blackberrypy/__init__.py
blackberrypy-0.0.1.dist-info/LICENSE
blackberrypy-0.0.1.dist-info/METADATA
blackberrypy-0.0.1.dist-info/WHEEL
blackberrypy-0.0.1.dist-info/top_level.txt
blackberrypy-0.0.1.dist-info/RECORD
