Metadata-Version: 2.1
Name: blackberrypy
Version: 0.0.1
Summary: Rubik's cube solver Python module
Home-page: https://github.com/Spatial-Innovations/BlackberryPy
Author: Spatial Innovations
Author-email: spatialinnovations@gmail.com
License: UNKNOWN
Platform: UNKNOWN
Classifier: Programming Language :: Python :: 3
Classifier: License :: OSI Approved :: GNU General Public License v2 or later (GPLv2+)
Classifier: Operating System :: OS Independent
